frontengine/__init__.py
frontengine/show/__init__.py
frontengine/show/base_widget.py
frontengine/show/gif/__init__.py
frontengine/show/gif/paint_gif.py
frontengine/show/image/__init__.py
frontengine/show/image/paint_image.py
frontengine/show/load/__init__.py
frontengine/show/load/load_someone_make_ui.py
frontengine/show/particle/__init__.py
frontengine/show/particle/particle_model.py
frontengine/show/particle/particle_scene.py
frontengine/show/particle/particle_ui.py
frontengine/show/particle/particle_utils.py
frontengine/show/scene/__init__.py
frontengine/show/scene/extend_graphic_scene.py
frontengine/show/scene/extend_graphic_view.py
frontengine/show/scene/scene.py
frontengine/show/sound_player/__init__.py
frontengine/show/sound_player/sound_effect.py
frontengine/show/sound_player/sound_player.py
frontengine/show/text/__init__.py
frontengine/show/text/draw_text.py
frontengine/show/video/__init__.py
frontengine/show/video/video_player.py
frontengine/show/web/__init__.py
frontengine/show/web/webview.py
frontengine/system_tray/__init__.py
frontengine/system_tray/extend_system_tray.py
frontengine/ui/__init__.py
frontengine/ui/main_ui.py
frontengine/ui/color/__init__.py
frontengine/ui/color/global_color.py
frontengine/ui/dialog/__init__.py
frontengine/ui/dialog/choose_file_dialog.py
frontengine/ui/dialog/save_file_dialog.py
frontengine/ui/menu/__init__.py
frontengine/ui/menu/help_menu.py
frontengine/ui/menu/how_to_menu.py
frontengine/ui/menu/language_menu.py
frontengine/ui/page/__init__.py
frontengine/ui/page/utils.py
frontengine/ui/page/control_center/__init__.py
frontengine/ui/page/control_center/control_center_ui.py
frontengine/ui/page/gif/__init__.py
frontengine/ui/page/gif/gif_setting_ui.py
frontengine/ui/page/image/__init__.py
frontengine/ui/page/image/image_setting_ui.py
frontengine/ui/page/particle/__init__.py
frontengine/ui/page/particle/particle_setting_ui.py
frontengine/ui/page/scene_setting/__init__.py
frontengine/ui/page/scene_setting/scene_manager.py
frontengine_dev-0.0.93.dist-info/licenses/LICENSE
frontengine_dev-0.0.93.dist-info/METADATA
frontengine_dev-0.0.93.dist-info/WHEEL
frontengine_dev-0.0.93.dist-info/top_level.txt
frontengine_dev-0.0.93.dist-info/RECORD
