Metadata-Version: 2.4
Name: frontengine_dev
Version: 0.0.93
Summary: FrontEngine is use-define frontview or only use like screen saver
Author-email: JE-Chen <jechenmailman@gmail.com>
Project-URL: Homepage, https://github.com/Intergration-Automation-Testing/FrontEngine
Project-URL: Code, https://github.com/Intergration-Automation-Testing/FrontEngine
Classifier: Programming Language :: Python :: 3.10
Classifier: Development Status :: 2 - Pre-Alpha
Classifier: Environment :: Win32 (MS Windows)
Classifier: Environment :: MacOS X
Classifier: Environment :: X11 Applications
Classifier: Operating System :: OS Independent
Requires-Python: >=3.10
License-File: LICENSE
Requires-Dist: PySide6==6.10.0
Requires-Dist: qt-material
Dynamic: license-file
